halfspace/__init__.py
halfspace/figure.py
halfspace/theme.py
halfspace/fonts/inter/Inter-Black-slnt=0.ttf
halfspace/fonts/inter/Inter-Bold-slnt=0.ttf
halfspace/fonts/inter/Inter-ExtraBold-slnt=0.ttf
halfspace/fonts/inter/Inter-ExtraLight-slnt=0.ttf
halfspace/fonts/inter/Inter-Light-slnt=0.ttf
halfspace/fonts/inter/Inter-Medium-slnt=0.ttf
halfspace/fonts/inter/Inter-Regular-slnt=0.ttf
halfspace/fonts/inter/Inter-SemiBold-slnt=0.ttf
halfspace/fonts/inter/Inter-Thin-slnt=0.ttf
halfspace/fonts/playfair/PlayfairDisplay-Black.ttf
halfspace/fonts/playfair/PlayfairDisplay-BlackItalic.ttf
halfspace/fonts/playfair/PlayfairDisplay-Bold.ttf
halfspace/fonts/playfair/PlayfairDisplay-BoldItalic.ttf
halfspace/fonts/playfair/PlayfairDisplay-ExtraBold.ttf
halfspace/fonts/playfair/PlayfairDisplay-ExtraBoldItalic.ttf
halfspace/fonts/playfair/PlayfairDisplay-Italic.ttf
halfspace/fonts/playfair/PlayfairDisplay-Medium.ttf
halfspace/fonts/playfair/PlayfairDisplay-MediumItalic.ttf
halfspace/fonts/playfair/PlayfairDisplay-Regular.ttf
halfspace/fonts/playfair/PlayfairDisplay-SemiBold.ttf
halfspace/fonts/playfair/PlayfairDisplay-SemiBoldItalic.ttf
halfspace/images/halfspace.png
halfspace/images/halfspace_inverted.png
halfspace-0.36.dist-info/METADATA
halfspace-0.36.dist-info/WHEEL
halfspace-0.36.dist-info/top_level.txt
halfspace-0.36.dist-info/RECORD
