Metadata-Version: 2.1
Name: halfspace
Version: 0.36
Summary: Core Halfspace python library
Home-page: https://halfspace.ai/
Author: Andreas Sogaard
Author-email: as@halfspace.io
License: UNKNOWN
Keywords: halfspace
Platform: UNKNOWN
Requires-Dist: matplotlib
Requires-Dist: seaborn
